rhml_client/ModelWrapper.py
rhml_client/__init__.py
rhml_client/setup_db.py
rhml_client/UI/__init__.py
rhml_client/UI/__main__.py
rhml_client/UI/ui_server.py
rhml_client/UI/helpers/__init__.py
rhml_client/UI/helpers/add_new_model.py
rhml_client/UI/helpers/configuration.py
rhml_client/UI/helpers/create_new_version.py
rhml_client/UI/helpers/db_record_to_dictionary.py
rhml_client/UI/helpers/deploy.py
rhml_client/UI/helpers/get_model_versions_static_data.py
rhml_client/UI/helpers/get_models_list.py
rhml_client/UI/helpers/model_naming.py
rhml_client/UI/helpers/packer.py
rhml_client/UI/helpers/random_string.py
rhml_client/UI/helpers/remove_model.py
rhml_client/UI/helpers/restore_file.py
rhml_client/UI/helpers/scan_folder.py
rhml_client/UI/helpers/set_model_version_active.py
rhml_client/UI/helpers/set_new_deploy_destination.py
rhml_client/UI/helpers/update_metadata_and_deployables.py
rhml_client-0.1.dist-info/LICENCE.txt
rhml_client-0.1.dist-info/METADATA
rhml_client-0.1.dist-info/WHEEL
rhml_client-0.1.dist-info/top_level.txt
rhml_client-0.1.dist-info/RECORD
